dj_channels_pubsub/__init__.py
dj_channels_pubsub/apps.py
dj_channels_pubsub/layer.py
dj_channels_pubsub/layers.py
dj_channels_pubsub/utils.py
dj_channels_pubsub/test_utils/__init__.py
dj_channels_pubsub/test_utils/test_app/__init__.py
dj_channels_pubsub/test_utils/test_app/admin.py
dj_channels_pubsub/test_utils/test_app/apps.py
dj_channels_pubsub/test_utils/test_app/models.py
dj_channels_pubsub/test_utils/test_app/migrations/__init__.py
dj_channels_pubsub-0.1.0.dist-info/AUTHORS.rst
dj_channels_pubsub-0.1.0.dist-info/LICENSE
dj_channels_pubsub-0.1.0.dist-info/METADATA
dj_channels_pubsub-0.1.0.dist-info/WHEEL
dj_channels_pubsub-0.1.0.dist-info/top_level.txt
dj_channels_pubsub-0.1.0.dist-info/RECORD
