Metadata-Version: 2.1
Name: dj-channels-pubsub
Version: 0.1.0
Summary: Django Channels Layer for Google PubSub
Home-page: https://github.com/bgervan/dj-channels-pubsub
Author: Benjamin Gervan
Author-email: bgervan@webstormit.com
License: MIT
Keywords: dj-channels-pubsub
Platform: UNKNOWN
Classifier: Development Status :: 3 - Alpha
Classifier: Framework :: Django :: 2.1
Classifier: Intended Audience :: Developers
Classifier: License :: OSI Approved :: BSD License
Classifier: Natural Language :: English
Classifier: Programming Language :: Python :: 2
Classifier: Programming Language :: Python :: 2.7
Classifier: Programming Language :: Python :: 3
Classifier: Programming Language :: Python :: 3.5
Classifier: Programming Language :: Python :: 3.6
License-File: LICENSE
License-File: AUTHORS.rst
Requires-Dist: channels (<4)
Requires-Dist: google-cloud-pubsub (==2.7.0)
